text_perturbation/__init__.py
text_perturbation/helper.py
text_perturbation/perturbation.py
text_perturbation-0.1.5.dist-info/METADATA
text_perturbation-0.1.5.dist-info/WHEEL
text_perturbation-0.1.5.dist-info/RECORD
