Metadata-Version: 2.1
Name: text_perturbation
Version: 0.1.5
Summary: This project is about the NLP task for text perturbation using different methods.
License: MIT
Author: dhirajpoddar
Author-email: dhirajpodar@gmail.com
Requires-Python: >=3.10,<4.0
Classifier: License :: OSI Approved :: MIT License
Classifier: Programming Language :: Python :: 3
Classifier: Programming Language :: Python :: 3.10
Classifier: Programming Language :: Python :: 3.11
Classifier: Programming Language :: Python :: 3.12
Requires-Dist: flake8 (>=7.1.1,<8.0.0)
Requires-Dist: nlpaug (>=1.1.11,<2.0.0)
Requires-Dist: nltk (>=3.8.2,<4.0.0)
Requires-Dist: pandas (>=2.2.2,<3.0.0)
Requires-Dist: pytest (>=8.3.2,<9.0.0)
Requires-Dist: transformers (>=4.44.0,<5.0.0)
